arclet/alconna/__init__.py
arclet/alconna/_internal/__init__.py
arclet/alconna/_internal/_analyser.py
arclet/alconna/_internal/_argv.py
arclet/alconna/_internal/_handlers.py
arclet/alconna/_internal/_header.py
arclet/alconna/_internal/_util.py
arclet/alconna/action.py
arclet/alconna/args.py
arclet/alconna/argv.py
arclet/alconna/arparma.py
arclet/alconna/base.py
arclet/alconna/builtin.py
arclet/alconna/completion.py
arclet/alconna/config.py
arclet/alconna/constraint.py
arclet/alconna/core.py
arclet/alconna/duplication.py
arclet/alconna/exceptions.py
arclet/alconna/formatter.py
arclet/alconna/i18n/.config.json
arclet/alconna/i18n/.lang.schema.json
arclet/alconna/i18n/.template.json
arclet/alconna/i18n/.template.schema.json
arclet/alconna/i18n/__init__.py
arclet/alconna/i18n/en-US.json
arclet/alconna/i18n/zh-CN.json
arclet/alconna/manager.py
arclet/alconna/model.py
arclet/alconna/model.pyi
arclet/alconna/output.py
arclet/alconna/py.typed
arclet/alconna/stub.py
arclet/alconna/typing.py
arclet_alconna-1.8.43.dist-info/METADATA
arclet_alconna-1.8.43.dist-info/WHEEL
arclet_alconna-1.8.43.dist-info/entry_points.txt
arclet_alconna-1.8.43.dist-info/licenses/LICENSE
arclet_alconna-1.8.43.dist-info/RECORD
