Metadata-Version: 2.1
Name: arclet-alconna
Version: 1.8.43
Summary: A High-performance, Generality, Humane Command Line Arguments Parser Library.
Keywords: command,argparse,fast,alconna,cli,command-line,parsing,optparse
Author-Email: RF-Tar-Railt <rf_tar_railt@qq.com>
License: MIT
Classifier: Typing :: Typed
Classifier: Development Status :: 5 - Production/Stable
Classifier: License :: OSI Approved :: MIT License
Classifier: Programming Language :: Python :: 3.8
Classifier: Programming Language :: Python :: 3.9
Classifier: Programming Language :: Python :: 3.10
Classifier: Programming Language :: Python :: 3.11
Classifier: Programming Language :: Python :: 3.12
Classifier: Programming Language :: Python :: 3.13
Classifier: Operating System :: OS Independent
Project-URL: documentation, https://arcletproject.github.io/docs/alconna/tutorial
Project-URL: repository, https://github.com/ArcletProject/Alconna
Requires-Python: >=3.9
Requires-Dist: typing-extensions>=4.5.0
Requires-Dist: nepattern<1.0.0,>=0.7.7
Requires-Dist: tarina<0.8.0,>=0.7.0
Provides-Extra: full
Requires-Dist: arclet-alconna-tools>=0.2.0; extra == "full"
